{"id":"evt_20260503_310","source":{"name":"Twitter @gCaptain","provider":"social-media"},"title":"Strait of Hormuz Traffic Collapses as US Blockade and Iran Tolls Reshape Global Shipping","summary":"Daily vessel traffic through the Strait of Hormuz collapsed from approximately 100 ships per day to a handful, as the dual pressure of US naval blockade and Iranian toll demands reshaped global shipping patterns and energy supply chains.","contents":"## Strait of Hormuz Shipping Collapse\n\n### Traffic Reduction\nVessel traffic through the Strait of Hormuz experienced a dramatic collapse, dropping from roughly 3,000 ships monthly (approximately 100 per day) to just a handful of daily transits. The reduction resulted from the combined effect of the US naval blockade enforced since April 13 and Iran's imposition of transit tolls.\n\n### Dual Pressure Campaign\nThe US enforced a complete naval blockade preventing all ships from traveling to or from Iranian ports, while CENTCOM confirmed 45 commercial vessels received turn-around orders. Simultaneously, Iran claimed to collect tolls from ships seeking safe passage, with Deputy Speaker Hamidreza Haji Bababei asserting that first toll revenues reached Iran's Central Bank.\n\n### Global Supply Chain Impact\nThe virtual closure of one of the world's most critical shipping chokepoints — through which roughly 20-30% of global petroleum typically transits — triggered massive rerouting of commercial traffic. Shipping companies diverted vessels via the Cape of Good Hope, adding 10-14 days to transit times and significantly increasing costs.\n\n### Oil Market Effects\nOil prices remained elevated above $120 per barrel amid reports of an extended blockade. Russian crude exports paradoxically rose to 7.1 million barrels per day in March, with export revenues nearly doubling from $9.7 billion to $19 billion, partially offsetting the impact of Ukrainian strikes on Russian oil infrastructure.\n\n### Industry Response\nOFAC warned maritime industry participants against paying Iranian tolls, threatening sanctions on both US and non-US persons involved. Major shipping companies continued routing around the Cape, accepting increased costs over sanctions risk.","date_published":"2026-05-03T07:00:00Z","date_event":"2026-05-02T20:00:00Z","links":[{"url":"https://www.bbc.com/news/articles/c3v2l2qq9qlo","label":"BBC - Strait of Hormuz shipping sanctions"}],"image_urls":[],"geo":{"lat":26.56,"lon":56.25,"country":"Iran","region":"Strait of Hormuz","city":"Strait of Hormuz"},"topics":["maritime","strait-of-hormuz","shipping","blockade","oil","supply-chain"],"confidence":0.93,"ingested_at":"2026-05-03T07:30:06Z"}