{"id":"evt_20260430_b1_15","source":{"name":"Twitter @ArmedForcesPhil","provider":"social-media"},"title":"China Deploys Naval and Air Patrols Near Scarborough Shoal in Response to Philippines-US Balikatan Drills","summary":"China's military conducted combat readiness patrols with naval and air forces near Scarborough Shoal amid the ongoing Balikatan exercises led by the Philippines and U.S. The patrols respond to the annual joint drills from April 20 to May 8, 2026, involving forces from Australia, New Zealand, the Philippines, and the United States to demonstrate advanced weapons and readiness. Tensions escalated as the exercises featured multinational counter-landing live-fire operations at Palawan, Philippines.","contents":"# China Deploys Naval and Air Patrols Near Scarborough Shoal in Response to Philippines-US Balikatan Drills\n\n## Overview\nOn April 30, 2026, China's military announced naval and air forces held combat readiness patrols near the disputed Scarborough Shoal in the South China Sea, directly responding to the expanded Balikatan exercises. These annual joint military drills, running from April 20 to May 8, unite troops from the Philippines, United States, Australia, and New Zealand to showcase advanced weapons capabilities and operational readiness amid rising regional tensions. A notable event during Balikatan included counter-landing live-fire exercises at Long Point Beach, Brgy. Aporawan, Aborlan, Palawan, Philippines, on April 27, 2026, where multinational forces posed with national flags post-training. While no specific Armed Forces of the Philippines (AFP) official remains named in reports, the exercises involve Philippine military leadership coordinating with U.S. and allied partners in South China Sea operations. China's actions highlight ongoing disputes over Scarborough Shoal, claimed by both nations, intensifying strategic competition in the region. Balikatan, traditionally bilateral, has grown to include more allies, focusing on interoperability and deterrence against potential aggression.\n\n## Location\n- **Where**: Scarborough Shoal, South China Sea (Philippines)\n- **Country**: Unknown\n\n## Source Attribution\nCoverage tracked from the ArmedForcesPhil beat (twitter-armed-forces-phil). News article URL provides primary attribution. The OSINT collection process anchors events to citation URLs given Twitter API access constraints.\n\n## Tags\nosint, armedforcesphil, breaking-news\n","date_published":"2026-04-30T19:30:00Z","geo":{"lat":0.0,"lon":0.0,"country":"Unknown","region":"","city":""},"links":[{"url":"https://chinaglobalsouth.com/2026/04/30/china-scarborough-shoal-patrols-philippines-us-balikatan-drills/","label":"News article cited by @ArmedForcesPhil beat"},{"url":"https://twitter.com/ArmedForcesPhil","label":"@ArmedForcesPhil (timeline)"}],"image_urls":[],"topics":["osint","armedforcesphil","breaking-news"],"confidence":0.65,"ingested_at":"2026-04-30T19:53:07Z"}